{ "backgroundcolor":"#43637c",
 "compressionlevel":-1,
 "height":10,
 "infinite":false,
 "layers":[
        {
         "data":[0, 0, 0, 0, 0, 0, 0, 0, 0, 0, 0, 0, 0, 0, 0, 0, 0, 0, 0, 0, 0, 0, 0, 0, 0, 0, 0, 0, 0, 0, 0, 0, 0, 0, 0, 0, 0, 0, 0, 0, 0, 0, 0, 0, 0, 0, 0, 0, 0, 0, 0, 0, 0, 0, 0, 0, 0, 0, 0, 0, 0, 0, 0, 0, 0, 0, 44, 0, 0, 0, 0, 0, 0, 0, 0, 0, 0, 0, 0, 0, 0, 0, 0, 0, 0, 0, 0, 0, 0, 0, 5, 0, 44, 0, 0, 0, 0, 0, 0, 0, 45, 46, 47, 0, 0, 5, 0, 0, 0, 0, 44, 0, 0, 2, 0, 0, 0, 0, 0, 0, 5, 0, 0, 0, 0, 0, 0, 2, 2, 2, 0, 0, 0, 0, 0, 50, 51, 51, 51, 51, 51, 51, 51, 51, 51, 51, 51, 51, 51, 52],
         "height":10,
         "id":1,
         "name":"Walls",
         "opacity":1,
         "type":"tilelayer",
         "visible":true,
         "width":15,
         "x":0,
         "y":0
        }],
 "nextlayerid":2,
 "nextobjectid":1,
 "orientation":"orthogonal",
 "renderorder":"right-down",
 "tiledversion":"1.7.2",
 "tileheight":128,
 "tilesets":[
        {
         "firstgid":1,
         "source":"tileset.json"
        }],
 "tilewidth":128,
 "type":"map",
 "version":"1.6",
 "width":15
}